package_name/__init__.py
package_name/file1_name.py
package_name/file2_name.py
criar_pacote_processamento-0.1.dist-info/METADATA
criar_pacote_processamento-0.1.dist-info/WHEEL
criar_pacote_processamento-0.1.dist-info/top_level.txt
criar_pacote_processamento-0.1.dist-info/RECORD
