Metadata-Version: 2.2
Name: criar_pacote_processamento
Version: 0.1
Summary: Bootcamp Dio
Home-page: https://github.com/pabloafer10/desafio_criar_pacote_processamento
Author: Pablo Fernandes
Author-email: pabloafer10@hotmail.com
Requires-Python: >=3.8
Dynamic: author
Dynamic: author-email
Dynamic: description
Dynamic: description-content-type
Dynamic: home-page
Dynamic: requires-python
Dynamic: summary
